domain2idna/__about__.py
domain2idna/__init__.py
domain2idna/cli.py
domain2idna/converter.py
domain2idna/helpers.py
domain2idna-1.12.4.dist-info/licenses/LICENSE
domain2idna-1.12.4.dist-info/METADATA
domain2idna-1.12.4.dist-info/WHEEL
domain2idna-1.12.4.dist-info/entry_points.txt
domain2idna-1.12.4.dist-info/top_level.txt
domain2idna-1.12.4.dist-info/RECORD
