Metadata-Version: 2.4
Name: domain2idna
Version: 1.12.4
Summary: The tool to convert a domain or a file with a list of domain to the famous IDNA format.
Home-page: https://github.com/PyFunceble/domain2idna
Author: funilrys
Author-email: contact@funilrys.com
License: MIT https://raw.githubusercontent.com/PyFunceble/domain2idna/master/LICENSE
Keywords: Python,domain,idna
Platform: any
Classifier: Environment :: Console
Classifier: Topic :: Internet
Classifier: Development Status :: 5 - Production/Stable
Classifier: Intended Audience :: Developers
Classifier: Programming Language :: Python
Classifier: Programming Language :: Python :: 3
Classifier: License :: OSI Approved :: MIT License
Requires-Python: >=3.6.2, <4
License-File: LICENSE
Requires-Dist: setuptools>=65.5.1
Requires-Dist: colorama
Provides-Extra: test
Requires-Dist: tox; extra == "test"
Requires-Dist: coverage; extra == "test"
Provides-Extra: dev
Requires-Dist: bandit; extra == "dev"
Requires-Dist: flake8; extra == "dev"
Requires-Dist: isort; extra == "dev"
Requires-Dist: pylint; extra == "dev"
Requires-Dist: black; extra == "dev"
Provides-Extra: full
Requires-Dist: bandit; extra == "full"
Requires-Dist: flake8; extra == "full"
Requires-Dist: colorama; extra == "full"
Requires-Dist: setuptools>=65.5.1; extra == "full"
Requires-Dist: isort; extra == "full"
Requires-Dist: tox; extra == "full"
Requires-Dist: coverage; extra == "full"
Requires-Dist: pylint; extra == "full"
Requires-Dist: black; extra == "full"
Dynamic: author
Dynamic: author-email
Dynamic: classifier
Dynamic: description
Dynamic: description-content-type
Dynamic: home-page
Dynamic: keywords
Dynamic: license
Dynamic: license-file
Dynamic: platform
Dynamic: provides-extra
Dynamic: requires-dist
Dynamic: requires-python
Dynamic: summary
